flask_bourbon/__init__.py
flask_bourbon/blueprint.py
flask_bourbon-0.0.4.dist-info/DESCRIPTION.rst
flask_bourbon-0.0.4.dist-info/METADATA
flask_bourbon-0.0.4.dist-info/RECORD
flask_bourbon-0.0.4.dist-info/WHEEL
flask_bourbon-0.0.4.dist-info/metadata.json
flask_bourbon-0.0.4.dist-info/top_level.txt
