Metadata-Version: 2.0
Name: flask-bourbon
Version: 0.0.4
Summary: Flask + Bourbon makes you swagger
Home-page: UNKNOWN
Author: Chris Wacek
Author-email: cwacek@gmail.com
License: MIT
Platform: UNKNOWN
Classifier: Programming Language :: Python :: 2
Classifier: Programming Language :: Python :: 2.7
Classifier: Programming Language :: Python :: 3
Classifier: Programming Language :: Python :: 3.5
Classifier: Intended Audience :: Developers
Classifier: Development Status :: 4 - Beta
Classifier: License :: OSI Approved :: MIT License
Classifier: Operating System :: OS Independent
Requires-Dist: flask
Requires-Dist: python-jsonschema-objects (~=0.3.2)
Requires-Dist: pyyaml
